fretlabel/__init__.py
fretlabel/console.py
fretlabel/ff.py
fretlabel/fretlabel_gui.py
fretlabel-0.2.1.dist-info/LICENSE
fretlabel-0.2.1.dist-info/METADATA
fretlabel-0.2.1.dist-info/WHEEL
fretlabel-0.2.1.dist-info/top_level.txt
fretlabel-0.2.1.dist-info/RECORD
