Metadata-Version: 2.2
Name: fretlabel
Version: 0.2.1
Summary: PyMOL plugin to interactively label nucleic acids with fluorophores in silico
Author-email: Fabio Steffen <fabio.steffen@chem.uzh.ch>, "Roland K.O. Sigel" <roland.sigel@chem.uzh.ch>, Richard Börner <richard.boerner@hs-mittweida.de>
License: GPL-3.0-or-later
Project-URL: Repository, https://github.com/RNA-FRETools/fretlabel
Project-URL: Documentation, https://rna-fretools.github.io/fretlabel/
Project-URL: Issues, https://rna-fretools.github.io/fretlabel/issues
Keywords: FRET,single-molecule,molecular dynamics,PDB,fluorescence labeling,AMBERDYES
Classifier: Programming Language :: Python
Classifier: License :: OSI Approved :: GNU General Public License v3 or later (GPLv3+)
Classifier: Operating System :: OS Independent
Classifier: Framework :: Jupyter
Classifier: Topic :: Scientific/Engineering :: Bio-Informatics
Requires-Python: >=3.10
License-File: LICENSE
Requires-Dist: pandas
Requires-Dist: biopandas
Provides-Extra: dev
Requires-Dist: bumpver; extra == "dev"
Provides-Extra: docs
Requires-Dist: lmfit; extra == "docs"
Requires-Dist: fretraj; extra == "docs"
Requires-Dist: jupyter-book; extra == "docs"
Requires-Dist: ipywidgets; extra == "docs"
Requires-Dist: matplotlib; extra == "docs"
Requires-Dist: seaborn; extra == "docs"
